z3c.traverser-2.0-py3.9-nspkg.pth
z3c/traverser/README.rst
z3c/traverser/__init__.py
z3c/traverser/browser.py
z3c/traverser/configure.zcml
z3c/traverser/interfaces.py
z3c/traverser/namespace.py
z3c/traverser/namespace.rst
z3c/traverser/tests.py
z3c/traverser/traverser.py
z3c/traverser/stackinfo/BROWSER.rst
z3c/traverser/stackinfo/README.rst
z3c/traverser/stackinfo/__init__.py
z3c/traverser/stackinfo/configure.zcml
z3c/traverser/stackinfo/consumer.py
z3c/traverser/stackinfo/ftesting.zcml
z3c/traverser/stackinfo/interfaces.py
z3c/traverser/stackinfo/tests.py
z3c/traverser/stackinfo/traversing.py
z3c/traverser/stackinfo/testing/__init__.py
z3c/traverser/stackinfo/testing/configure.zcml
z3c/traverser/stackinfo/testing/consumer.py
z3c/traverser/stackinfo/testing/views.py
z3c/traverser/viewlet/BROWSER.rst
z3c/traverser/viewlet/README.rst
z3c/traverser/viewlet/__init__.py
z3c/traverser/viewlet/browser.py
z3c/traverser/viewlet/configure.zcml
z3c/traverser/viewlet/ftesting.zcml
z3c/traverser/viewlet/namespace.py
z3c/traverser/viewlet/tests.py
z3c/traverser/viewlet/testing/__init__.py
z3c/traverser/viewlet/testing/app.py
z3c/traverser/viewlet/testing/inner.pt
z3c/traverser/viewlet/testing/nested.pt
z3c/traverser/viewlet/testing/outer.pt
z3c/traverser/viewlet/testing/test.pt
z3c.traverser-2.0.dist-info/LICENSE.rst
z3c.traverser-2.0.dist-info/METADATA
z3c.traverser-2.0.dist-info/WHEEL
z3c.traverser-2.0.dist-info/namespace_packages.txt
z3c.traverser-2.0.dist-info/top_level.txt
z3c.traverser-2.0.dist-info/RECORD
