Metadata-Version: 2.1
Name: z3c.traverser
Version: 2.0
Summary: Pluggable Traversers And URL handling utilities
Home-page: https://github.com/zopefoundation/z3c.traverser
Author: Zope Foundation and Contributors
Author-email: zope-dev@zope.dev
License: ZPL 2.1
Keywords: zope3 traverser pluggable plugin viewlet
Classifier: Development Status :: 5 - Production/Stable
Classifier: Environment :: Web Environment
Classifier: Intended Audience :: Developers
Classifier: License :: OSI Approved :: Zope Public License
Classifier: Programming Language :: Python
Classifier: Programming Language :: Python :: 3
Classifier: Programming Language :: Python :: 3.7
Classifier: Programming Language :: Python :: 3.8
Classifier: Programming Language :: Python :: 3.9
Classifier: Programming Language :: Python :: 3.10
Classifier: Programming Language :: Python :: 3.11
Classifier: Programming Language :: Python :: Implementation :: CPython
Classifier: Natural Language :: English
Classifier: Operating System :: OS Independent
Classifier: Topic :: Internet :: WWW/HTTP
Classifier: Framework :: Zope :: 3
Requires-Python: >=3.7
License-File: LICENSE.rst
Requires-Dist: setuptools
Requires-Dist: zope.component
Requires-Dist: zope.contentprovider
Requires-Dist: zope.interface
Requires-Dist: zope.publisher
Requires-Dist: zope.traversing
Requires-Dist: zope.viewlet
Requires-Dist: zope.testrunner
Provides-Extra: test
Requires-Dist: WebTest ; extra == 'test'
Requires-Dist: zope.app.appsetup ; extra == 'test'
Requires-Dist: zope.app.publication ; extra == 'test'
Requires-Dist: zope.app.wsgi (>=4.0.0a4) ; extra == 'test'
Requires-Dist: zope.authentication ; extra == 'test'
Requires-Dist: zope.browserpage ; extra == 'test'
Requires-Dist: zope.container ; extra == 'test'
Requires-Dist: zope.error ; extra == 'test'
Requires-Dist: zope.principalregistry ; extra == 'test'
Requires-Dist: zope.security ; extra == 'test'
Requires-Dist: zope.site ; extra == 'test'
Requires-Dist: zope.testbrowser ; extra == 'test'
Requires-Dist: zope.testing ; extra == 'test'
Requires-Dist: zope.testrunner (>=4.3.1) ; extra == 'test'
